{
  "kind": "singleType",
  "collectionName": "home_pages",
  "info": {
    "name": "HomePage",
    "description": ""
  },
  "options": {
    "increments": true,
    "timestamps": true,
    "draftAndPublish": false
  },
  "pluginOptions": {},
  "attributes": {
    "Footer": {
      "type": "component",
      "repeatable": false,
      "component": "block.footer",
      "required": true
    },
    "SEO": {
      "type": "component",
      "repeatable": false,
      "component": "reusable.seo"
    },
    "Header": {
      "type": "component",
      "repeatable": false,
      "component": "block.header"
    }
  }
}
